Metadata-Version: 2.1
Name: epic-games-free
Version: 0.1.4
Summary: An Epic Games Store free games API wrapper
Home-page: https://github.com/r-liner/epic_games_free/
Author: liner
Author-email: contact.liner999@gmail.com
License: MIT
Classifier: Programming Language :: Python :: 3
Classifier: Programming Language :: Python :: 3.10
Classifier: Programming Language :: Python :: 3.11
Classifier: License :: OSI Approved :: MIT License
Classifier: Operating System :: OS Independent
License-File: LICENSE
